DeepSearchLite/DeepSearchLite.py
DeepSearchLite/__init__.py
DeepSearchLite-0.2.1.dist-info/LICENSE
DeepSearchLite-0.2.1.dist-info/METADATA
DeepSearchLite-0.2.1.dist-info/WHEEL
DeepSearchLite-0.2.1.dist-info/top_level.txt
DeepSearchLite-0.2.1.dist-info/RECORD
