Metadata-Version: 2.1
Name: DeepSearchLite
Version: 0.2.1
Summary: A package for similarity search for any type of data. Use your own feature extractor and data loader and use this package to perform similarity search.
Home-page: https://github.com/ibadrather/DeepSearchLite
Author: Ibad Rather
Author-email: ibad.rather.ir@gmail.com
Classifier: Development Status :: 3 - Alpha
Classifier: Intended Audience :: Developers
Classifier: License :: OSI Approved :: MIT License
Classifier: Operating System :: OS Independent
Classifier: Programming Language :: Python :: 3
Classifier: Programming Language :: Python :: 3.8
Classifier: Programming Language :: Python :: 3.9
Classifier: Programming Language :: Python :: 3.10
Requires-Python: >=3.8
License-File: LICENSE
Requires-Dist: numpy
Requires-Dist: pandas
Requires-Dist: Pillow
Requires-Dist: faiss-cpu
Requires-Dist: tqdm
